{
  "name": "GranuleStatusReply",
  "file_identifier": 7563104,
  "fdb_version": "7.3.75",
  "source_file": "fdbclient/include/fdbclient/BlobWorkerInterface.h",
  "vtable": [
    36,
    85,
    4,
    12,
    68,
    80,
    81,
    82,
    20,
    28,
    72,
    36,
    44,
    83,
    52,
    60,
    84,
    76
  ],
  "fields": [
    {
      "name": "acknowledgeToken",
      "cpp_type": "uint64_t",
      "type": "scalar",
      "vtable_slot": 0,
      "wire_size": 8,
      "wire_alignment": 8,
      "inline": true
    },
    {
      "name": "sequence",
      "cpp_type": "int64_t",
      "type": "scalar",
      "vtable_slot": 1,
      "wire_size": 8,
      "wire_alignment": 8,
      "inline": true
    },
    {
      "name": "granuleRange",
      "cpp_type": "KeyRange",
      "type": "bytes",
      "vtable_slot": 2,
      "wire_size": 4,
      "wire_alignment": 4,
      "inline": false
    },
    {
      "name": "doSplit",
      "cpp_type": "bool",
      "type": "scalar",
      "vtable_slot": 3,
      "wire_size": 1,
      "wire_alignment": 1,
      "inline": true
    },
    {
      "name": "writeHotSplit",
      "cpp_type": "bool",
      "type": "scalar",
      "vtable_slot": 4,
      "wire_size": 1,
      "wire_alignment": 1,
      "inline": true
    },
    {
      "name": "initialSplitTooBig",
      "cpp_type": "bool",
      "type": "scalar",
      "vtable_slot": 5,
      "wire_size": 1,
      "wire_alignment": 1,
      "inline": true
    },
    {
      "name": "continueEpoch",
      "cpp_type": "int64_t",
      "type": "scalar",
      "vtable_slot": 6,
      "wire_size": 8,
      "wire_alignment": 8,
      "inline": true
    },
    {
      "name": "continueSeqno",
      "cpp_type": "int64_t",
      "type": "scalar",
      "vtable_slot": 7,
      "wire_size": 8,
      "wire_alignment": 8,
      "inline": true
    },
    {
      "name": "granuleID",
      "cpp_type": "UID",
      "type": "struct",
      "vtable_slot": 8,
      "wire_size": 4,
      "wire_alignment": 4,
      "inline": false
    },
    {
      "name": "startVersion",
      "cpp_type": "Version",
      "type": "scalar",
      "vtable_slot": 9,
      "wire_size": 8,
      "wire_alignment": 8,
      "inline": true
    },
    {
      "name": "blockedVersion",
      "cpp_type": "Version",
      "type": "scalar",
      "vtable_slot": 10,
      "wire_size": 8,
      "wire_alignment": 8,
      "inline": true
    },
    {
      "name": "mergeCandidate",
      "cpp_type": "bool",
      "type": "scalar",
      "vtable_slot": 11,
      "wire_size": 1,
      "wire_alignment": 1,
      "inline": true
    },
    {
      "name": "originalEpoch",
      "cpp_type": "int64_t",
      "type": "scalar",
      "vtable_slot": 12,
      "wire_size": 8,
      "wire_alignment": 8,
      "inline": true
    },
    {
      "name": "originalSeqno",
      "cpp_type": "int64_t",
      "type": "scalar",
      "vtable_slot": 13,
      "wire_size": 8,
      "wire_alignment": 8,
      "inline": true
    },
    {
      "name": "proposedSplitKey",
      "cpp_type": "Optional\u003cKey\u003e",
      "type": "optional",
      "vtable_slot": 14,
      "wire_size": 0,
      "wire_alignment": 0,
      "inline": false
    }
  ]
}
